grifftools/__init__.py
grifftools/cli.py
grifftools/func.py
grifftools/lib.py
grifftools/shell.py
grifftools-0.0.2.dist-info/licenses/LICENSE
grifftools-0.0.2.dist-info/METADATA
grifftools-0.0.2.dist-info/WHEEL
grifftools-0.0.2.dist-info/top_level.txt
grifftools-0.0.2.dist-info/RECORD
