Metadata-Version: 2.4
Name: grifftools
Version: 0.0.2
License-File: LICENSE
Requires-Dist: more_itertools
Requires-Dist: toolz
Requires-Dist: fire
Requires-Dist: dill
Dynamic: license-file
Dynamic: requires-dist
